validation_semantic-1.1.4.dist-info/METADATA
validation_semantic-1.1.4.dist-info/WHEEL
validation_semantic/__init__.py
validation_semantic/__init__.pyi
validation_semantic/py.typed
validation_semantic/validation_semantic.abi3.so
validation_semantic-1.1.4.dist-info/RECORD
