Metadata-Version: 2.4
Name: validation_semantic
Version: 1.1.4
Summary: Library pendeteksi kalimat atau kata untuk validasi semantik input menggunakan LLM
Home-Page: https://github.com/herros27/validation_semantic
Author: Kemas Khairunsyah <khairunsyah8935@gmail.com>
Author-email: Kemas Khairunsyah <khairunsyah8935@gmail.com>
License: MIT
Project-URL: Homepage, https://github.com/herros27/validation_semantic
Project-URL: Source Code, https://github.com/herros27/validation_semantic
